gb_menu/__init__.py
gb_menu/action.py
gb_menu/choice.py
gb_menu/menu.py
gb_menu-1.0.0.dist-info/LICENSE
gb_menu-1.0.0.dist-info/METADATA
gb_menu-1.0.0.dist-info/WHEEL
gb_menu-1.0.0.dist-info/top_level.txt
gb_menu-1.0.0.dist-info/RECORD
