Metadata-Version: 2.1
Name: gb-menu
Version: 1.0.0
Summary: A lightweight Python library useful for creating powerful yet simple console-based user interfaces
Home-page: https://github.com/gbeard2/gb-menu
Author: Garrett Beard
Author-email: beardgarrett077@gmail.com
License: UNKNOWN
Platform: UNKNOWN
Classifier: Programming Language :: Python :: 3
Classifier: License :: OSI Approved :: MIT License
Classifier: Operating System :: OS Independent
Requires-Python: >=3.6
